libname/Super.py
libname/__init__.py
sici3-0.0.1.dist-info/METADATA
sici3-0.0.1.dist-info/WHEEL
sici3-0.0.1.dist-info/top_level.txt
sici3-0.0.1.dist-info/RECORD
